image_processing_pkg/__init__.py
image_processing_pkg/processing/__init__.py
image_processing_pkg/processing/advanced.py
image_processing_pkg/processing/basic.py
image_processing_pkg/processing/filters.py
image_processing_pkg/utils/__init__.py
image_processing_pkg/utils/io.py
image_processing_pkg/utils/metadata.py
krevoniz_unique_img_proc_pkg-0.1.0.dist-info/licenses/LICENSE
tests/__init__.py
tests/run_tests.py
tests/test_advanced.py
tests/test_basic.py
tests/test_filters.py
tests/test_utils.py
krevoniz_unique_img_proc_pkg-0.1.0.dist-info/METADATA
krevoniz_unique_img_proc_pkg-0.1.0.dist-info/WHEEL
krevoniz_unique_img_proc_pkg-0.1.0.dist-info/top_level.txt
krevoniz_unique_img_proc_pkg-0.1.0.dist-info/RECORD
