Metadata-Version: 2.4
Name: krevoniz_unique_img_proc_pkg
Version: 0.1.0
Summary: Pacote de processamento de imagens usando Python
Home-page: https://github.com/krevoniz/image_processing_pkg
Author: Krevoniz
Author-email: krevoniz@gmail.com
Classifier: Development Status :: 4 - Beta
Classifier: Intended Audience :: Developers
Classifier: License :: OSI Approved :: MIT License
Classifier: Natural Language :: Portuguese (Brazilian)
Classifier: Operating System :: OS Independent
Classifier: Programming Language :: Python :: 3.8
Classifier: Programming Language :: Python :: 3.9
Classifier: Topic :: Software Development :: Libraries :: Python Modules
Classifier: Topic :: Scientific/Engineering :: Image Processing
Requires-Python: >=3.8
License-File: LICENSE
Requires-Dist: numpy>=1.20.0
Requires-Dist: Pillow>=8.0.0
Requires-Dist: scipy>=1.6.0
Requires-Dist: matplotlib>=3.3.0
Requires-Dist: scikit-image>=0.18.0
Requires-Dist: opencv-python>=4.5.0
Dynamic: author
Dynamic: author-email
Dynamic: classifier
Dynamic: description
Dynamic: description-content-type
Dynamic: home-page
Dynamic: license-file
Dynamic: requires-dist
Dynamic: requires-python
Dynamic: summary
